[
  {
    "movie": {
"identity": 105,
"labels": [
        "Movie"
      ],
"properties": {
"tagline": "Everything is connected",
"title": "Cloud Atlas",
"released": 2012
      }
    },
    "director": {
"identity": 108,
"labels": [
        "Person"
      ],
"properties": {
"name": "Tom Tykwer",
"born": 1965
      }
    }
  },
  {
    "movie": {
"identity": 105,
"labels": [
        "Movie"
      ],
"properties": {
"tagline": "Everything is connected",
"title": "Cloud Atlas",
"released": 2012
      }
    },
    "director": {
"identity": 6,
"labels": [
        "Person"
      ],
"properties": {
"name": "Lana Wachowski",
"born": 1965
      }
    }
  },
  {
    "movie": {
"identity": 105,
"labels": [
        "Movie"
      ],
"properties": {
"tagline": "Everything is connected",
"title": "Cloud Atlas",
"released": 2012
      }
    },
    "director": {
"identity": 5,
"labels": [
        "Person"
      ],
"properties": {
"name": "Lilly Wachowski",
"born": 1967
      }
    }
  },
  {
    "movie": {
"identity": 116,
"labels": [
        "Movie"
      ],
"properties": {
"tagline": "Freedom! Forever!",
"title": "V for Vendetta",
"released": 2006
      }
    },
    "director": {
"identity": 25,
"labels": [
        "Person"
      ],
"properties": {
"name": "James Marshall",
"born": 1967
      }
    }
  },
  {
    "movie": {
"identity": 10,
"labels": [
        "Movie"
      ],
"properties": {
"tagline": "Everything that has a beginning has an end",
"title": "The Matrix Revolutions",
"released": 2003
      }
    },
    "director": {
"identity": 6,
"labels": [
        "Person"
      ],
"properties": {
"name": "Lana Wachowski",
"born": 1965
      }
    }
  },
  {
    "movie": {
"identity": 10,
"labels": [
        "Movie"
      ],
"properties": {
"tagline": "Everything that has a beginning has an end",
"title": "The Matrix Revolutions",
"released": 2003
      }
    },
    "director": {
"identity": 5,
"labels": [
        "Person"
      ],
"properties": {
"name": "Lilly Wachowski",
"born": 1967
      }
    }
  },
  {
    "movie": {
"identity": 9,
"labels": [
        "Movie"
      ],
"properties": {
"tagline": "Free your mind",
"title": "The Matrix Reloaded",
"released": 2003
      }
    },
    "director": {
"identity": 6,
"labels": [
        "Person"
      ],
"properties": {
"name": "Lana Wachowski",
"born": 1965
      }
    }
  },
  {
    "movie": {
"identity": 9,
"labels": [
        "Movie"
      ],
"properties": {
"tagline": "Free your mind",
"title": "The Matrix Reloaded",
"released": 2003
      }
    },
    "director": {
"identity": 5,
"labels": [
        "Person"
      ],
"properties": {
"name": "Lilly Wachowski",
"born": 1967
      }
    }
  },
  {
    "movie": {
"identity": 0,
"labels": [
        "Movie"
      ],
"properties": {
"tagline": "Welcome to the Real World",
"title": "The Matrix",
"released": 1999
      }
    },
    "director": {
"identity": 6,
"labels": [
        "Person"
      ],
"properties": {
"name": "Lana Wachowski",
"born": 1965
      }
    }
  },
  {
    "movie": {
"identity": 0,
"labels": [
        "Movie"
      ],
"properties": {
"tagline": "Welcome to the Real World",
"title": "The Matrix",
"released": 1999
      }
    },
    "director": {
"identity": 5,
"labels": [
        "Person"
      ],
"properties": {
"name": "Lilly Wachowski",
"born": 1967
      }
    }
  }
]